BPfold/__init__.py
BPfold/evaluate.py
BPfold/kit.py
BPfold/predict.py
BPfold/configs/config.yaml
BPfold/dataset/RNAseq.py
BPfold/dataset/__init__.py
BPfold/model/BPfoldNet.py
BPfold/model/__init__.py
BPfold/model/loss_and_metric.py
BPfold/model/pos_embed.py
BPfold/paras/key.energy
BPfold/util/RNA_kit.py
BPfold/util/__init__.py
BPfold/util/base_pair_motif.py
BPfold/util/base_pair_probability.py
BPfold/util/data_sampler.py
BPfold/util/hook_features.py
BPfold/util/misc.py
BPfold/util/postprocess.py
BPfold/util/yaml_config.py
bpfold-0.3.1.dist-info/licenses/LICENSE
bpfold-0.3.1.dist-info/METADATA
bpfold-0.3.1.dist-info/WHEEL
bpfold-0.3.1.dist-info/entry_points.txt
bpfold-0.3.1.dist-info/top_level.txt
bpfold-0.3.1.dist-info/RECORD
