Metadata-Version: 2.4
Name: BPfold
Version: 0.3.1
Summary: Deep generalizable prediction of RNA secondary structure via base pair motif energy.
Author-email: Heqin Zhu <zhuheqin1@gmail.com>
License: MIT License
Project-URL: Homepage, https://github.com/heqin-zhu/BPfold
Project-URL: Issues, https://github.com/heqin-zhu/BPfold/issues
Keywords: RNA,secondary structure,fold
Classifier: Programming Language :: Python :: 3
Classifier: License :: OSI Approved :: MIT License
Classifier: Operating System :: OS Independent
Requires-Python: >=3.8
License-File: LICENSE
Dynamic: license-file
